pymtts/__init__.py
pymtts/async_mtts.py
pymtts/tools.py
pymtts-0.2.1.dist-info/LICENSE
pymtts-0.2.1.dist-info/METADATA
pymtts-0.2.1.dist-info/WHEEL
pymtts-0.2.1.dist-info/top_level.txt
pymtts-0.2.1.dist-info/RECORD
