Metadata-Version: 2.1
Name: pymtts
Version: 0.2.1
Summary: A python package for using Azure smart AI speech
Home-page: https://github.com/p1ay8y3ar/pymtts
Author: p1ay8y3ar
Author-email: p1ay8y3ar@gmail.com
Classifier: Programming Language :: Python :: 3
Classifier: License :: OSI Approved :: MIT License
Classifier: Operating System :: OS Independent
Requires-Python: >=3.6
License-File: LICENSE
Requires-Dist: aiohttp
Requires-Dist: setuptools
Requires-Dist: websockets
